Workbook
Name RevenueRange: Table1[Revenue]
Name TotalRevenue: 'Sales Data'!$O$2

Sheet sales_import
A1: Date | B1: OrderID | C1: Product | D1: Region | E1: UnitsSold | F1: UnitPrice
A2: 46254 | B2: ORD006 | C2: Mouse | D2: Oslo | E2: 8 | F2: 250
A3: 46255 | B3: ORD007 | C3: Webcam | D3: Bergen | E3: 5 | F3: 600
A4: 46256 | B4: ORD008 | C4: Headset | D4: Trondheim | E4: 6 | F4: 450
A5: 46257 | B5: ORD009 | C5: Printer | D5: Stavanger | E5: 2 | F5: 1800

Sheet Sales Data
A1: Date | B1: Order ID | C1: Product | D1: Category | E1: Region | F1: Salesperson | G1: Units Sold | H1: Unit price | I1: Revenue | J1: Cost | K1: Profit | L1: Taks Amount | M1: Taks Rate | O1: Total Revenue | P1: Average Revenue
A2: 46235 | B2: ORD001 | C2: Laptop | D2: =_xlfn.XLOOKUP(C2,Products!$A$2:$A$6,Products!$B$2:$B$6) -> Electronics | E2: Oslo | F2: Anna | G2: 3 | H2: =_xlfn.XLOOKUP(C2,Products!$A$2:$A$6,Products!$C$2:$C$6) -> 1200 | I2: =G2*H2 -> 3600 | J2: 2400 | K2: =I2-J2 -> 1200 | L2: =I2*$M$2 -> 900 | M2: 0.25 | O2: =SUM(I2:I6) -> 8120 | P2: =AVERAGE(I2:I6) -> 1624
A3: 46237 | B3: ORD002 | C3: Monitor | D3: =_xlfn.XLOOKUP(C3,Products!$A$2:$A$6,Products!$B$2:$B$6) -> Electronics | E3: Bergen | F3: Erik | G3: 5 | H3: =_xlfn.XLOOKUP(C3,Products!$A$2:$A$6,Products!$C$2:$C$6) -> 350 | I3: =G3*H3 -> 1750 | J3: 1100 | K3: =I3-J3 -> 650 | L3: =I3*$M$2 -> 437.5
A4: 46239 | B4: ORD003 | C4: Office Chair | D4: =_xlfn.XLOOKUP(C4,Products!$A$2:$A$6,Products!$B$2:$B$6) -> Furniture | E4: Oslo | F4: Maria | G4: 4 | H4: =_xlfn.XLOOKUP(C4,Products!$A$2:$A$6,Products!$C$2:$C$6) -> 280 | I4: =G4*H4 -> 1120 | J4: 700 | K4: =I4-J4 -> 420 | L4: =I4*$M$2 -> 280
A5: 46244 | B5: ORD005 | C5: Desk | D5: =_xlfn.XLOOKUP(C5,Products!$A$2:$A$6,Products!$B$2:$B$6) -> Furniture | E5: Stavanger | F5: Anna | G5: 2 | H5: =_xlfn.XLOOKUP(C5,Products!$A$2:$A$6,Products!$C$2:$C$6) -> 450 | I5: =G5*H5 -> 900 | J5: 600 | K5: =I5-J5 -> 300 | L5: =I5*$M$2 -> 225
A6: 46241 | B6: ORD004 | C6: Keybord | D6: =_xlfn.XLOOKUP(C6,Products!$A$2:$A$6,Products!$B$2:$B$6) -> Electronics | E6: Trondheim | F6: Lars | G6: 10 | H6: =_xlfn.XLOOKUP(C6,Products!$A$2:$A$6,Products!$C$2:$C$6) -> 75 | I6: =G6*H6 -> 750 | J6: 400 | K6: =I6-J6 -> 350 | L6: =I6*$M$2 -> 187.5

Sheet Products
A1: Product | B1: Category | C1: Unit Price
A2: Laptop | B2: Electronics | C2: 1200
A3: Monitor | B3: Electronics | C3: 350
A4: Office Chair | B4: Furniture | C4: 280
A5: Keybord | B5: Electronics | C5: 75
A6: Desk | B6: Furniture | C6: 450

Sheet Dashboard
A1: Sales Analysis Dashboard
A3: Total Revenue | C3: Total Profit | E3: Total Units Sold | G3: Average Revenue
A4: =SUM('Sales Data'!I2:I6) -> 8120 | C4: =SUM('Sales Data'!K2:K6) -> 2920 | E4: =SUM('Sales Data'!G2:G6) -> 24 | G4: =AVERAGE('Sales Data'!I2:I6) -> 1624
